frutils/__init__.py
frutils/defaults.py
frutils/doc.py
frutils/exceptions.py
frutils/frkl.info
frutils/frutils.py
frutils/frutils_cli.py
frutils/jinja2_filters.py
frutils/jinja2_filters_2.py
frutils/parameters.py
frutils/properties.py
frutils/config/__init__.py
frutils/config/cnf.py
frutils/tasks/__init__.py
frutils/tasks/callback.py
frutils/tasks/tasks.py
frutils/utils/__init__.py
frutils/utils/ssh.py
frutils-1.0.1.dist-info/AUTHORS.rst
frutils-1.0.1.dist-info/LICENSE
frutils-1.0.1.dist-info/METADATA
frutils-1.0.1.dist-info/WHEEL
frutils-1.0.1.dist-info/entry_points.txt
frutils-1.0.1.dist-info/top_level.txt
frutils-1.0.1.dist-info/RECORD
