Metadata-Version: 2.1
Name: frutils
Version: 1.0.1
Summary: Utilities for frkl projects.
Home-page: https://gitlab.com/frkl/frutils
Author: Markus Binsteiner
Author-email: makkus@frkl.io
License: "The Parity Public License 6.0.0"
Platform: any
Classifier: Development Status :: 4 - Beta
Classifier: Programming Language :: Python
Requires-Python: !=3.0.*,!=3.1.*,!=3.2.*,!=3.3.*,>=2.7
Requires-Dist: requests[security] (>=2.20.0)
Requires-Dist: pyOpenSSL (>=0.14)
Requires-Dist: cryptography (>=1.3.4)
Requires-Dist: idna (>=2.0.0)
Requires-Dist: six (>=1.12.0)
Requires-Dist: jinja2 (>=2.10)
Requires-Dist: future (>=0.16.0)
Requires-Dist: ruamel.yaml[jinja2] (>=0.15.81)
Requires-Dist: Cerberus (>=1.2)
Requires-Dist: pprintpp (>=0.4.0)
Requires-Dist: pp-ez (>=0.2.0)
Requires-Dist: blessings (>=1.7)
Requires-Dist: passlib (>=1.7.1)
Requires-Dist: plumbum (>=1.6.7)
Requires-Dist: frkl.mdv (==1.7.5)
Requires-Dist: dogpile.cache (>=0.7.1)
Requires-Dist: tqdm (>=4.31.1)
Requires-Dist: treelib (>=1.5.3)
Requires-Dist: stevedore (>=1.30.1)
Requires-Dist: halo (>=0.0.28)
Requires-Dist: toml (>=0.10.0)
Requires-Dist: Click (>=7.0)
Requires-Dist: click-log (>=0.3.2)
Requires-Dist: click-completion (==0.5.0)
Requires-Dist: text-unidecode (==1.2)
Requires-Dist: python-slugify (==3.0.2)
Requires-Dist: inflection (==0.3.1)
Requires-Dist: pexpect (==4.7.0)
Requires-Dist: logzero (>=1.5.0)
Requires-Dist: fasteners (>=0.15)
Requires-Dist: cursor (==1.2.0)
Requires-Dist: jinja2schema (>=0.1.4)
Requires-Dist: dpath (==1.4.2)
Requires-Dist: appdirs (==1.4.3)
Requires-Dist: omegaconf (==1.3.0)
Provides-Extra: develop
Requires-Dist: flake8 ; extra == 'develop'
Requires-Dist: ipython ; extra == 'develop'
Requires-Dist: black ; extra == 'develop'
Requires-Dist: pip-tools ; extra == 'develop'
Requires-Dist: pre-commit ; extra == 'develop'
Requires-Dist: watchdog ; extra == 'develop'
Requires-Dist: wheel ; extra == 'develop'
Requires-Dist: pipdeptree ; extra == 'develop'
Requires-Dist: isort ; extra == 'develop'
Requires-Dist: mu-repo ; extra == 'develop'
Provides-Extra: docs
Requires-Dist: Sphinx ; extra == 'docs'
Requires-Dist: recommonmark ; extra == 'docs'
Provides-Extra: testing
Requires-Dist: pytest ; extra == 'testing'
Requires-Dist: more-itertools (==5.0.0) ; extra == 'testing'
Requires-Dist: pytest-cov ; extra == 'testing'
Requires-Dist: tox ; extra == 'testing'
